run_as_task.py
run_as_task-0.1.4.dist-info/LICENSE
run_as_task-0.1.4.dist-info/METADATA
run_as_task-0.1.4.dist-info/WHEEL
run_as_task-0.1.4.dist-info/RECORD
