Metadata-Version: 2.1
Name: run_as_task
Version: 0.1.4
Summary: `run_as_task` is a Python package that allows scripts to escalate their privileges to Administrator (Local Service) without requiring UAC approval.
Home-page: https://github.com/th-yoo/run_as_task
License: MIT
Keywords: admin,windows,elevation,privileges,task scheduler
Author: th yoo
Author-email: taihyungyoo@gmail.com
Requires-Python: >=3.9,<4.0
Classifier: License :: OSI Approved :: MIT License
Classifier: Programming Language :: Python :: 3
Classifier: Programming Language :: Python :: 3.9
Classifier: Programming Language :: Python :: 3.10
Classifier: Programming Language :: Python :: 3.11
Classifier: Programming Language :: Python :: 3.12
Requires-Dist: pywin32 (>=300) ; sys_platform == "win32"
